tree_sitter_netlinx/__init__.py
tree_sitter_netlinx/__init__.pyi
tree_sitter_netlinx/_binding.pyd
tree_sitter_netlinx/binding.c
tree_sitter_netlinx/py.typed
tree_sitter_netlinx/queries/folds.scm
tree_sitter_netlinx/queries/highlights-g4api.scm
tree_sitter_netlinx/queries/highlights-snapi.scm
tree_sitter_netlinx/queries/highlights-unicodelib.scm
tree_sitter_netlinx/queries/highlights.scm
tree_sitter_netlinx/queries/locals.scm
tree_sitter_netlinx/queries/tags.scm
tree_sitter_netlinx-1.0.4.dist-info/licenses/LICENSE
tree_sitter_netlinx-1.0.4.dist-info/METADATA
tree_sitter_netlinx-1.0.4.dist-info/WHEEL
tree_sitter_netlinx-1.0.4.dist-info/top_level.txt
tree_sitter_netlinx-1.0.4.dist-info/RECORD
