Metadata-Version: 2.4
Name: tree-sitter-netlinx
Version: 1.0.4
Summary: NetLinx grammar for tree-sitter
License: MIT
Project-URL: Homepage, https://github.com/Norgate-AV/tree-sitter-netlinx
Keywords: incremental,parsing,tree-sitter,netlinx,amx,harman
Classifier: Intended Audience :: Developers
Classifier: License :: OSI Approved :: MIT License
Classifier: Topic :: Software Development :: Compilers
Classifier: Topic :: Text Processing :: Linguistic
Classifier: Typing :: Typed
Requires-Python: >=3.10
License-File: LICENSE
Provides-Extra: core
Requires-Dist: tree-sitter~=0.24; extra == "core"
Dynamic: license-file
